thalesians/__init__.py
thalesians/pypes/__init__.py
thalesians/pypes/zmq.py
thalesians.pypes-0.0.1.dist-info/LICENSE
thalesians.pypes-0.0.1.dist-info/METADATA
thalesians.pypes-0.0.1.dist-info/WHEEL
thalesians.pypes-0.0.1.dist-info/top_level.txt
thalesians.pypes-0.0.1.dist-info/RECORD
